pyhangouts2/__init__.py
pyhangouts2/gchatty.py
pyhangouts2/genconf.py
pyhangouts2/selectoptions.py
pyhangouts2/thechatwouldbewatching.py
pyhangouts2-1.1.2.dist-info/METADATA
pyhangouts2-1.1.2.dist-info/WHEEL
pyhangouts2-1.1.2.dist-info/licenses/LICENSE
pyhangouts2-1.1.2.dist-info/RECORD
