Metadata-Version: 2.4
Name: pyhangouts2
Version: 1.1.2
Summary: A Selenium-based Python 3 library for Google Chat.
Project-URL: Homepage, https://code.nolog.cz/NexusSfan/googlechatutils
Project-URL: Issues, https://code.nolog.cz/NexusSfan/googlechatutils/issues
Author-email: NexusSfan <nexussfan@duck.com>
License-Expression: GPL-3.0-or-later
License-File: LICENSE
Classifier: Operating System :: OS Independent
Classifier: Programming Language :: Python :: 3
Requires-Python: >=3.13
Requires-Dist: beautifulsoup4>=4.13.4
Requires-Dist: lxml>=5.4.0
Requires-Dist: selenium>=4.33.0
